bloodhound_nmap/__init__.py
bloodhound_nmap/main.py
bloodhound_nmap-0.1.2.dist-info/METADATA
bloodhound_nmap-0.1.2.dist-info/WHEEL
bloodhound_nmap-0.1.2.dist-info/entry_points.txt
bloodhound_nmap-0.1.2.dist-info/RECORD
