Metadata-Version: 2.4
Name: bloodhound-nmap
Version: 0.1.2
Summary: Transform Nmap scan results into BloodHound-compatible OpenGraph format for network analysis
Project-URL: Homepage, https://github.com/rreichel3/bloodhound-nmap
Project-URL: Documentation, https://github.com/rreichel3/bloodhound-nmap#readme
Project-URL: Repository, https://github.com/rreichel3/bloodhound-nmap.git
Project-URL: Bug Tracker, https://github.com/rreichel3/bloodhound-nmap/issues
Author-email: Your Name <your.email@example.com>
Maintainer-email: Your Name <your.email@example.com>
License: MIT
Keywords: bloodhound,network,nmap,opengraph,scanning,security
Classifier: Development Status :: 4 - Beta
Classifier: Environment :: Console
Classifier: Intended Audience :: Information Technology
Classifier: Intended Audience :: System Administrators
Classifier: License :: OSI Approved :: MIT License
Classifier: Operating System :: OS Independent
Classifier: Programming Language :: Python :: 3
Classifier: Programming Language :: Python :: 3.9
Classifier: Programming Language :: Python :: 3.10
Classifier: Programming Language :: Python :: 3.11
Classifier: Programming Language :: Python :: 3.12
Classifier: Programming Language :: Python :: 3.13
Classifier: Topic :: Security
Classifier: Topic :: System :: Networking :: Monitoring
Classifier: Topic :: System :: Systems Administration
Requires-Python: >=3.9
Requires-Dist: bloodhound-opengraph>=1.0.0
Requires-Dist: python-nmap>=0.7.1
